LICENSE.txt
MANIFEST.in
README.md
pyproject.toml
setup.cfg
src/gui_api_tkinter/__init__.py
src/gui_api_tkinter/build_info.py
src/gui_api_tkinter/cfg.py
src/gui_api_tkinter/constants.py
src/gui_api_tkinter/constants_version.py
src/gui_api_tkinter/svc.py
src/gui_api_tkinter.egg-info/PKG-INFO
src/gui_api_tkinter.egg-info/SOURCES.txt
src/gui_api_tkinter.egg-info/dependency_links.txt
src/gui_api_tkinter.egg-info/requires.txt
src/gui_api_tkinter.egg-info/top_level.txt
src/gui_api_tkinter/guiapi/__init__.py
src/gui_api_tkinter/guiapi/gui_api_server.py
src/gui_api_tkinter/guiapi/gui_api_tkinter.py
src/gui_api_tkinter/harness/__init__.py
src/gui_api_tkinter/harness/client.py
src/gui_api_tkinter/harness/gui_api_harness.py
src/gui_api_tkinter/harness/response.py
src/gui_api_tkinter/harness/widget_base.py
src/gui_api_tkinter/harness/widget_click.py
src/gui_api_tkinter/harness/widget_combobox.py
src/gui_api_tkinter/harness/widget_listbox.py
src/gui_api_tkinter/harness/widget_text.py