Metadata-Version: 2.4
Name: gui-api-tkinter
Version: 1.1.0
Summary: GUI API for interfacing and testing with tkinter
Author-email: "J. Arrizza" <cppgent0@gmail.com>
Maintainer-email: "J. Arrizza" <cppgent0@gmail.com>
License-Expression: MIT
Project-URL: Website, https://arrizza.com/python-gui-api-tkinter
Project-URL: Source, https://bitbucket.org/arrizza-public/gui-api-tkinter/src/master
Project-URL: Download, https://bitbucket.org/arrizza-public/gui-api-tkinter/get/master.zip
Keywords: gui,tkinter,test,verification
Classifier: Development Status :: 4 - Beta
Classifier: Environment :: Console
Classifier: Topic :: Utilities
Classifier: Intended Audience :: Developers
Classifier: Programming Language :: Python :: 3.10
Classifier: Programming Language :: Python :: 3.12
Requires-Python: >=3.9
License-File: LICENSE.txt
Requires-Dist: medver-pytest
Requires-Dist: jsmin
Requires-Dist: socket-oneline
Requires-Dist: falcon-logger
Dynamic: license-file
